linetimer/__init__.py
linetimer-0.1.5.dist-info/LICENSE
linetimer-0.1.5.dist-info/METADATA
linetimer-0.1.5.dist-info/WHEEL
linetimer-0.1.5.dist-info/top_level.txt
linetimer-0.1.5.dist-info/RECORD
