Metadata-Version: 2.1
Name: linetimer
Version: 0.1.5
Summary: A small Python class to quickly measure the time taken while executing a block of indented lines
Home-page: https://github.com/justasb/linetimer
Author: Justas Birgiolas, Chitral Verma, Pranshu Aggarwal
Author-email: jbirgio@gmail.com
License: UNKNOWN
Platform: UNKNOWN
Classifier: Programming Language :: Python :: 2
Classifier: Programming Language :: Python :: 3
Classifier: License :: OSI Approved :: MIT License
Classifier: Operating System :: OS Independent
License-File: LICENSE
